{
    "absl-py": {
        "cor-asv-ann": "1.2.0",
        "eynollah": "1.2.0",
        "ocrd_anybaseocr": "1.2.0",
        "ocrd_calamari": "1.2.0",
        "ocrd_keraslm": "1.2.0",
        "ocrd_kraken": "1.2.0",
        "ocrd_pc_segmentation": "0.15.0",
        "sbb_binarization": "1.2.0"
    },
    "gast": {
        "cor-asv-ann": "0.2.2",
        "eynollah": "0.4.0",
        "ocrd_anybaseocr": "0.4.0",
        "ocrd_calamari": "0.4.0",
        "ocrd_keraslm": "0.2.2",
        "ocrd_pc_segmentation": "0.4.0",
        "sbb_binarization": "0.4.0"
    },
    "grpcio": {
        "cor-asv-ann": "1.47.0",
        "eynollah": "1.47.0",
        "ocrd_anybaseocr": "1.47.0",
        "ocrd_calamari": "1.47.0",
        "ocrd_keraslm": "1.47.0",
        "ocrd_kraken": "1.47.0",
        "ocrd_pc_segmentation": "1.34.1",
        "sbb_binarization": "1.47.0"
    },
    "h5py": {
        "cor-asv-ann": "2.10.0",
        "eynollah": "3.7.0",
        "ocrd_anybaseocr": "3.7.0",
        "ocrd_calamari": "3.7.0",
        "ocrd_keraslm": "2.10.0",
        "ocrd_pc_segmentation": "3.1.0",
        "sbb_binarization": "3.7.0"
    },
    "imageio": {
        "ocrd_anybaseocr": "2.20.0",
        "ocrd_calamari": "2.20.0",
        "ocrd_cis": "2.20.0",
        "ocrd_kraken": "2.20.0",
        "ocrd_ocropy": "2.20.0",
        "ocrd_pc_segmentation": "2.4.1",
        "ocrd_segment": "2.20.0",
        "ocrd_typegroups_classifier": "2.20.0",
        "ocrd_wrap": "2.20.0"
    },
    "numpy": {
        "cor-asv-ann": "1.18.5",
        "ocrd_keraslm": "1.18.5",
        "ocrd_pc_segmentation": "1.19.5"
    },
    "protobuf": {
        "cor-asv-ann": "4.21.3",
        "eynollah": "3.19.4",
        "ocrd_anybaseocr": "3.19.4",
        "ocrd_calamari": "3.19.4",
        "ocrd_keraslm": "4.21.3",
        "ocrd_kraken": "3.19.4",
        "ocrd_pc_segmentation": "3.19.4",
        "sbb_binarization": "3.19.4"
    },
    "scikit-image": {
        "ocrd_anybaseocr": "0.19.3",
        "ocrd_calamari": "0.19.3",
        "ocrd_cis": "0.19.3",
        "ocrd_kraken": "0.19.2",
        "ocrd_pc_segmentation": "0.17.2",
        "ocrd_segment": "0.19.3",
        "ocrd_typegroups_classifier": "0.19.3",
        "ocrd_wrap": "0.19.3"
    },
    "six": {
        "cor-asv-ann": "1.16.0",
        "dinglehopper": "1.16.0",
        "eynollah": "1.16.0",
        "ocrd_anybaseocr": "1.16.0",
        "ocrd_calamari": "1.16.0",
        "ocrd_keraslm": "1.16.0",
        "ocrd_kraken": "1.16.0",
        "ocrd_ocropy": "1.16.0",
        "ocrd_pc_segmentation": "1.15.0",
        "ocrd_segment": "1.16.0",
        "ocrd_typegroups_classifier": "1.16.0",
        "sbb_binarization": "1.16.0"
    },
    "tensorboard": {
        "cor-asv-ann": "1.15.0",
        "eynollah": "2.9.1",
        "ocrd_anybaseocr": "2.9.1",
        "ocrd_calamari": "2.9.1",
        "ocrd_keraslm": "1.15.0",
        "ocrd_kraken": "2.9.1",
        "ocrd_pc_segmentation": "2.9.1",
        "sbb_binarization": "2.9.1"
    },
    "tensorflow": {
        "eynollah": "2.9.1",
        "ocrd_anybaseocr": "2.9.1",
        "ocrd_calamari": "2.9.1",
        "ocrd_pc_segmentation": "2.5.0",
        "sbb_binarization": "2.9.1"
    },
    "tensorflow-estimator": {
        "cor-asv-ann": "1.15.1",
        "eynollah": "2.9.0",
        "ocrd_anybaseocr": "2.9.0",
        "ocrd_calamari": "2.9.0",
        "ocrd_keraslm": "1.15.1",
        "ocrd_pc_segmentation": "2.5.0",
        "sbb_binarization": "2.9.0"
    },
    "torch": {
        "ocrd_anybaseocr": "1.12.0",
        "ocrd_kraken": "1.11.0",
        "ocrd_typegroups_classifier": "1.12.0"
    },
    "torchvision": {
        "ocrd_anybaseocr": "0.13.0",
        "ocrd_kraken": "0.12.0",
        "ocrd_typegroups_classifier": "0.13.0"
    }
}