[
    {
        "eval_workflow_id": "wf-data16_frak_simple_minimal_ocr-eval",
        "label": "Workflow on data 16_frak_simple_minimal_ocr",
        "metadata": {
            "ocr_workflow": {
                "@id": "https://github.com/OCR-D/quiver-back-end/blob/main/workflows/ocrd_workflows/minimal_ocr.txt",
                "label": "OCR Workflow minimal_ocr"
            },
            "eval_workflow": {
                "@id": "https://github.com/OCR-D/quiver-back-end/blob/main/workflows/ocrd_workflows/dinglehopper_eval.txt",
                "label": "Evaluation Workflow dinglehopper_eval"
            },
            "gt_workspace": {
                "@id": "https://github.com/OCR-D/quiver-data/blob/main/16_frak_simple_minimal_ocr.ocrd.zip",
                "label": "GT workspace 16th century Black letter simple layout"
            },
            "ocr_workspace": {
                "@id": "https://github.com/OCR-D/quiver-back-end/blob/main/workflows/results/16_frak_simple_minimal_ocr_ocr.zip",
                "label": "OCR workspace for 16_frak_simple_minimal_ocr"
            },
            "eval_workspace": {
                "@id": "https://github.com/OCR-D/quiver-back-end/blob/main/workflows/results/16_frak_simple_minimal_ocr_evaluation.zip",
                "label": "Evaluation workspace for 16_frak_simple_minimal_ocr"
            },
            "workflow_steps": {
                "ocrd-tesserocr-recognize": "{\"segmentation_level\": \"region\", \"textequiv_level\": \"word\", \"find_tables\": true, \"model\": \"Fraktur_GT4HistOCR\", \"dpi\": 0, \"padding\": 0, \"overwrite_segments\": false, \"overwrite_text\": true, \"shrink_polygons\": false, \"block_polygons\": false, \"find_staves\": false, \"sparse_text\": false, \"raw_lines\": false, \"char_whitelist\": \"\", \"char_blacklist\": \"\", \"char_unblacklist\": \"\", \"tesseract_parameters\": {}, \"xpath_parameters\": {}, \"xpath_model\": {}, \"auto_model\": false, \"oem\": \"DEFAULT\"}"
            },
            "workflow_model": "Fraktur_GT4HistOCR",
            "document_metadata": {
                "data_properties": {
                    "fonts": [
                        "Black Letter"
                    ],
                    "publication_century": "1500-1600",
                    "publication_decade": "",
                    "publication_year": "16th century",
                    "number_of_pages": 6,
                    "layout": "simple"
                }
            }
        },
        "evaluation_results": {
            "document_wide": {
                "wall_time": 26535,
                "cer": 0.13490219630962338,
                "cer_min_max": [
                    0.014285714285714285,
                    0.4184652278177458
                ]
            },
            "by_page": [
                {
                    "page_id": "phys_0001",
                    "cer": 0.0718562874251497
                },
                {
                    "page_id": "phys_0002",
                    "cer": 0.014285714285714285
                },
                {
                    "page_id": "phys_0003",
                    "cer": 0.4184652278177458
                },
                {
                    "page_id": "phys_0007",
                    "cer": 0.09135802469135802
                },
                {
                    "page_id": "phys_0021",
                    "cer": 0.13479623824451412
                },
                {
                    "page_id": "phys_0029",
                    "cer": 0.07865168539325842
                }
            ]
        }
    },
    {
        "eval_workflow_id": "wf-data17_frak_simple_minimal_ocr-eval",
        "label": "Workflow on data 17_frak_simple_minimal_ocr",
        "metadata": {
            "ocr_workflow": {
                "@id": "https://github.com/OCR-D/quiver-back-end/blob/main/workflows/ocrd_workflows/minimal_ocr.txt",
                "label": "OCR Workflow minimal_ocr"
            },
            "eval_workflow": {
                "@id": "https://github.com/OCR-D/quiver-back-end/blob/main/workflows/ocrd_workflows/dinglehopper_eval.txt",
                "label": "Evaluation Workflow dinglehopper_eval"
            },
            "gt_workspace": {
                "@id": "https://github.com/OCR-D/quiver-data/blob/main/17_frak_simple_minimal_ocr.ocrd.zip",
                "label": "GT workspace 17th century Black letter simple layout"
            },
            "ocr_workspace": {
                "@id": "https://github.com/OCR-D/quiver-back-end/blob/main/workflows/results/17_frak_simple_minimal_ocr_ocr.zip",
                "label": "OCR workspace for 17_frak_simple_minimal_ocr"
            },
            "eval_workspace": {
                "@id": "https://github.com/OCR-D/quiver-back-end/blob/main/workflows/results/17_frak_simple_minimal_ocr_evaluation.zip",
                "label": "Evaluation workspace for 17_frak_simple_minimal_ocr"
            },
            "workflow_steps": {
                "ocrd-tesserocr-recognize": "{\"segmentation_level\": \"region\", \"textequiv_level\": \"word\", \"find_tables\": true, \"model\": \"Fraktur_GT4HistOCR\", \"dpi\": 0, \"padding\": 0, \"overwrite_segments\": false, \"overwrite_text\": true, \"shrink_polygons\": false, \"block_polygons\": false, \"find_staves\": false, \"sparse_text\": false, \"raw_lines\": false, \"char_whitelist\": \"\", \"char_blacklist\": \"\", \"char_unblacklist\": \"\", \"tesseract_parameters\": {}, \"xpath_parameters\": {}, \"xpath_model\": {}, \"auto_model\": false, \"oem\": \"DEFAULT\"}"
            },
            "workflow_model": "Fraktur_GT4HistOCR",
            "document_metadata": {
                "data_properties": {
                    "fonts": [
                        "Black Letter"
                    ],
                    "publication_century": "1600-1700",
                    "publication_decade": "",
                    "publication_year": "17th century",
                    "number_of_pages": 3,
                    "layout": "simple"
                }
            }
        },
        "evaluation_results": {
            "document_wide": {
                "wall_time": 10490,
                "cer": 0.08427970798416445,
                "cer_min_max": [
                    0.05025996533795494,
                    0.10926118626430802
                ]
            },
            "by_page": [
                {
                    "page_id": "phys_0001",
                    "cer": 0.10926118626430802
                },
                {
                    "page_id": "phys_0002",
                    "cer": 0.09331797235023041
                },
                {
                    "page_id": "phys_0003",
                    "cer": 0.05025996533795494
                }
            ]
        }
    },
    {
        "eval_workflow_id": "wf-data18_frak_simple_minimal_ocr-eval",
        "label": "Workflow on data 18_frak_simple_minimal_ocr",
        "metadata": {
            "ocr_workflow": {
                "@id": "https://github.com/OCR-D/quiver-back-end/blob/main/workflows/ocrd_workflows/minimal_ocr.txt",
                "label": "OCR Workflow minimal_ocr"
            },
            "eval_workflow": {
                "@id": "https://github.com/OCR-D/quiver-back-end/blob/main/workflows/ocrd_workflows/dinglehopper_eval.txt",
                "label": "Evaluation Workflow dinglehopper_eval"
            },
            "gt_workspace": {
                "@id": "https://github.com/OCR-D/quiver-data/blob/main/18_frak_simple_minimal_ocr.ocrd.zip",
                "label": "GT workspace 18th century Black letter simple layout"
            },
            "ocr_workspace": {
                "@id": "https://github.com/OCR-D/quiver-back-end/blob/main/workflows/results/18_frak_simple_minimal_ocr_ocr.zip",
                "label": "OCR workspace for 18_frak_simple_minimal_ocr"
            },
            "eval_workspace": {
                "@id": "https://github.com/OCR-D/quiver-back-end/blob/main/workflows/results/18_frak_simple_minimal_ocr_evaluation.zip",
                "label": "Evaluation workspace for 18_frak_simple_minimal_ocr"
            },
            "workflow_steps": {
                "ocrd-tesserocr-recognize": "{\"segmentation_level\": \"region\", \"textequiv_level\": \"word\", \"find_tables\": true, \"model\": \"Fraktur_GT4HistOCR\", \"dpi\": 0, \"padding\": 0, \"overwrite_segments\": false, \"overwrite_text\": true, \"shrink_polygons\": false, \"block_polygons\": false, \"find_staves\": false, \"sparse_text\": false, \"raw_lines\": false, \"char_whitelist\": \"\", \"char_blacklist\": \"\", \"char_unblacklist\": \"\", \"tesseract_parameters\": {}, \"xpath_parameters\": {}, \"xpath_model\": {}, \"auto_model\": false, \"oem\": \"DEFAULT\"}"
            },
            "workflow_model": "Fraktur_GT4HistOCR",
            "document_metadata": {
                "data_properties": {
                    "fonts": [
                        "Black Letter"
                    ],
                    "publication_century": "1700-1800",
                    "publication_decade": "",
                    "publication_year": "18th century",
                    "number_of_pages": 1,
                    "layout": "simple"
                }
            }
        },
        "evaluation_results": {
            "document_wide": {
                "wall_time": 4999,
                "cer": 0.02493765586034913,
                "cer_min_max": [
                    0.02493765586034913,
                    0.02493765586034913
                ]
            },
            "by_page": [
                {
                    "page_id": "phys_0001",
                    "cer": 0.02493765586034913
                }
            ]
        }
    },
    {
        "eval_workflow_id": "wf-data16_ant_complex_minimal_ocr-eval",
        "label": "Workflow on data 16_ant_complex_minimal_ocr",
        "metadata": {
            "ocr_workflow": {
                "@id": "https://github.com/OCR-D/quiver-back-end/blob/main/workflows/ocrd_workflows/minimal_ocr.txt",
                "label": "OCR Workflow minimal_ocr"
            },
            "eval_workflow": {
                "@id": "https://github.com/OCR-D/quiver-back-end/blob/main/workflows/ocrd_workflows/dinglehopper_eval.txt",
                "label": "Evaluation Workflow dinglehopper_eval"
            },
            "gt_workspace": {
                "@id": "https://github.com/OCR-D/quiver-data/blob/main/16_ant_complex_minimal_ocr.ocrd.zip",
                "label": "GT workspace 16th century Antiqua complex layout"
            },
            "ocr_workspace": {
                "@id": "https://github.com/OCR-D/quiver-back-end/blob/main/workflows/results/16_ant_complex_minimal_ocr_ocr.zip",
                "label": "OCR workspace for 16_ant_complex_minimal_ocr"
            },
            "eval_workspace": {
                "@id": "https://github.com/OCR-D/quiver-back-end/blob/main/workflows/results/16_ant_complex_minimal_ocr_evaluation.zip",
                "label": "Evaluation workspace for 16_ant_complex_minimal_ocr"
            },
            "workflow_steps": {
                "ocrd-tesserocr-recognize": "{\"segmentation_level\": \"region\", \"textequiv_level\": \"word\", \"find_tables\": true, \"model\": \"Fraktur_GT4HistOCR\", \"dpi\": 0, \"padding\": 0, \"overwrite_segments\": false, \"overwrite_text\": true, \"shrink_polygons\": false, \"block_polygons\": false, \"find_staves\": false, \"sparse_text\": false, \"raw_lines\": false, \"char_whitelist\": \"\", \"char_blacklist\": \"\", \"char_unblacklist\": \"\", \"tesseract_parameters\": {}, \"xpath_parameters\": {}, \"xpath_model\": {}, \"auto_model\": false, \"oem\": \"DEFAULT\"}"
            },
            "workflow_model": "Fraktur_GT4HistOCR",
            "document_metadata": {
                "data_properties": {
                    "fonts": [
                        "Antiqua"
                    ],
                    "publication_century": "1500-1600",
                    "publication_decade": "",
                    "publication_year": "16th century",
                    "number_of_pages": 3,
                    "layout": "complex"
                }
            }
        },
        "evaluation_results": {
            "document_wide": {
                "wall_time": 10348,
                "cer": 0.10240852523716282,
                "cer_min_max": [
                    0.07124352331606218,
                    0.1306122448979592
                ]
            },
            "by_page": [
                {
                    "page_id": "phys_0007",
                    "cer": 0.07124352331606218
                },
                {
                    "page_id": "phys_0008",
                    "cer": 0.10536980749746708
                },
                {
                    "page_id": "phys_0009",
                    "cer": 0.1306122448979592
                }
            ]
        }
    },
    {
        "eval_workflow_id": "wf-data18_fontmix_complex_minimal_ocr-eval",
        "label": "Workflow on data 18_fontmix_complex_minimal_ocr",
        "metadata": {
            "ocr_workflow": {
                "@id": "https://github.com/OCR-D/quiver-back-end/blob/main/workflows/ocrd_workflows/minimal_ocr.txt",
                "label": "OCR Workflow minimal_ocr"
            },
            "eval_workflow": {
                "@id": "https://github.com/OCR-D/quiver-back-end/blob/main/workflows/ocrd_workflows/dinglehopper_eval.txt",
                "label": "Evaluation Workflow dinglehopper_eval"
            },
            "gt_workspace": {
                "@id": "https://github.com/OCR-D/quiver-data/blob/main/18_fontmix_complex_minimal_ocr.ocrd.zip",
                "label": "GT workspace 18th century Font Mix complex layout"
            },
            "ocr_workspace": {
                "@id": "https://github.com/OCR-D/quiver-back-end/blob/main/workflows/results/18_fontmix_complex_minimal_ocr_ocr.zip",
                "label": "OCR workspace for 18_fontmix_complex_minimal_ocr"
            },
            "eval_workspace": {
                "@id": "https://github.com/OCR-D/quiver-back-end/blob/main/workflows/results/18_fontmix_complex_minimal_ocr_evaluation.zip",
                "label": "Evaluation workspace for 18_fontmix_complex_minimal_ocr"
            },
            "workflow_steps": {
                "ocrd-tesserocr-recognize": "{\"segmentation_level\": \"region\", \"textequiv_level\": \"word\", \"find_tables\": true, \"model\": \"Fraktur_GT4HistOCR\", \"dpi\": 0, \"padding\": 0, \"overwrite_segments\": false, \"overwrite_text\": true, \"shrink_polygons\": false, \"block_polygons\": false, \"find_staves\": false, \"sparse_text\": false, \"raw_lines\": false, \"char_whitelist\": \"\", \"char_blacklist\": \"\", \"char_unblacklist\": \"\", \"tesseract_parameters\": {}, \"xpath_parameters\": {}, \"xpath_model\": {}, \"auto_model\": false, \"oem\": \"DEFAULT\"}"
            },
            "workflow_model": "Fraktur_GT4HistOCR",
            "document_metadata": {
                "data_properties": {
                    "fonts": [
                        "Antiqua",
                        "Black Letter"
                    ],
                    "publication_century": "1700-1800",
                    "publication_decade": "",
                    "publication_year": "18th century",
                    "number_of_pages": 4,
                    "layout": "complex"
                }
            }
        },
        "evaluation_results": {
            "document_wide": {
                "wall_time": 23078,
                "cer": 0.20433470587543373,
                "cer_min_max": [
                    0.04063745019920319,
                    0.43666666666666665
                ]
            },
            "by_page": [
                {
                    "page_id": "phys_0001",
                    "cer": 0.43666666666666665
                },
                {
                    "page_id": "phys_0002",
                    "cer": 0.04063745019920319
                },
                {
                    "page_id": "phys_0003",
                    "cer": 0.05536912751677853
                },
                {
                    "page_id": "phys_0004",
                    "cer": 0.28466557911908646
                }
            ]
        }
    },
    {
        "eval_workflow_id": "wf-data19_frak_simple_minimal_ocr-eval",
        "label": "Workflow on data 19_frak_simple_minimal_ocr",
        "metadata": {
            "ocr_workflow": {
                "@id": "https://github.com/OCR-D/quiver-back-end/blob/main/workflows/ocrd_workflows/minimal_ocr.txt",
                "label": "OCR Workflow minimal_ocr"
            },
            "eval_workflow": {
                "@id": "https://github.com/OCR-D/quiver-back-end/blob/main/workflows/ocrd_workflows/dinglehopper_eval.txt",
                "label": "Evaluation Workflow dinglehopper_eval"
            },
            "gt_workspace": {
                "@id": "https://github.com/OCR-D/quiver-data/blob/main/19_frak_simple_minimal_ocr.ocrd.zip",
                "label": "GT workspace 19th century Black letter simple layout"
            },
            "ocr_workspace": {
                "@id": "https://github.com/OCR-D/quiver-back-end/blob/main/workflows/results/19_frak_simple_minimal_ocr_ocr.zip",
                "label": "OCR workspace for 19_frak_simple_minimal_ocr"
            },
            "eval_workspace": {
                "@id": "https://github.com/OCR-D/quiver-back-end/blob/main/workflows/results/19_frak_simple_minimal_ocr_evaluation.zip",
                "label": "Evaluation workspace for 19_frak_simple_minimal_ocr"
            },
            "workflow_steps": {
                "ocrd-tesserocr-recognize": "{\"segmentation_level\": \"region\", \"textequiv_level\": \"word\", \"find_tables\": true, \"model\": \"Fraktur_GT4HistOCR\", \"dpi\": 0, \"padding\": 0, \"overwrite_segments\": false, \"overwrite_text\": true, \"shrink_polygons\": false, \"block_polygons\": false, \"find_staves\": false, \"sparse_text\": false, \"raw_lines\": false, \"char_whitelist\": \"\", \"char_blacklist\": \"\", \"char_unblacklist\": \"\", \"tesseract_parameters\": {}, \"xpath_parameters\": {}, \"xpath_model\": {}, \"auto_model\": false, \"oem\": \"DEFAULT\"}"
            },
            "workflow_model": "Fraktur_GT4HistOCR",
            "document_metadata": {
                "data_properties": {
                    "fonts": [
                        "Black Letter"
                    ],
                    "publication_century": "1800-1900",
                    "publication_decade": "",
                    "publication_year": "19th century",
                    "number_of_pages": 1,
                    "layout": "simple"
                }
            }
        },
        "evaluation_results": {
            "document_wide": {
                "wall_time": 7389,
                "cer": 0.004721435316336166,
                "cer_min_max": [
                    0.004721435316336166,
                    0.004721435316336166
                ]
            },
            "by_page": [
                {
                    "page_id": "phys_0001",
                    "cer": 0.004721435316336166
                }
            ]
        }
    },
    {
        "eval_workflow_id": "wf-data19_ant_simple_minimal_ocr-eval",
        "label": "Workflow on data 19_ant_simple_minimal_ocr",
        "metadata": {
            "ocr_workflow": {
                "@id": "https://github.com/OCR-D/quiver-back-end/blob/main/workflows/ocrd_workflows/minimal_ocr.txt",
                "label": "OCR Workflow minimal_ocr"
            },
            "eval_workflow": {
                "@id": "https://github.com/OCR-D/quiver-back-end/blob/main/workflows/ocrd_workflows/dinglehopper_eval.txt",
                "label": "Evaluation Workflow dinglehopper_eval"
            },
            "gt_workspace": {
                "@id": "https://github.com/OCR-D/quiver-data/blob/main/19_ant_simple_minimal_ocr.ocrd.zip",
                "label": "GT workspace 19th century Antiqua simple layout"
            },
            "ocr_workspace": {
                "@id": "https://github.com/OCR-D/quiver-back-end/blob/main/workflows/results/19_ant_simple_minimal_ocr_ocr.zip",
                "label": "OCR workspace for 19_ant_simple_minimal_ocr"
            },
            "eval_workspace": {
                "@id": "https://github.com/OCR-D/quiver-back-end/blob/main/workflows/results/19_ant_simple_minimal_ocr_evaluation.zip",
                "label": "Evaluation workspace for 19_ant_simple_minimal_ocr"
            },
            "workflow_steps": {
                "ocrd-tesserocr-recognize": "{\"segmentation_level\": \"region\", \"textequiv_level\": \"word\", \"find_tables\": true, \"model\": \"Fraktur_GT4HistOCR\", \"dpi\": 0, \"padding\": 0, \"overwrite_segments\": false, \"overwrite_text\": true, \"shrink_polygons\": false, \"block_polygons\": false, \"find_staves\": false, \"sparse_text\": false, \"raw_lines\": false, \"char_whitelist\": \"\", \"char_blacklist\": \"\", \"char_unblacklist\": \"\", \"tesseract_parameters\": {}, \"xpath_parameters\": {}, \"xpath_model\": {}, \"auto_model\": false, \"oem\": \"DEFAULT\"}"
            },
            "workflow_model": "Fraktur_GT4HistOCR",
            "document_metadata": {
                "data_properties": {
                    "fonts": [
                        "Antiqua"
                    ],
                    "publication_century": "1800-1900",
                    "publication_decade": "",
                    "publication_year": "19th century",
                    "number_of_pages": 3,
                    "layout": "simple"
                }
            }
        },
        "evaluation_results": {
            "document_wide": {
                "wall_time": 16637,
                "cer": 0.08328200324172261,
                "cer_min_max": [
                    0.04055496264674493,
                    0.12192262602579132
                ]
            },
            "by_page": [
                {
                    "page_id": "phys_0001",
                    "cer": 0.08736842105263158
                },
                {
                    "page_id": "phys_0002",
                    "cer": 0.04055496264674493
                },
                {
                    "page_id": "phys_0003",
                    "cer": 0.12192262602579132
                }
            ]
        }
    },
    {
        "eval_workflow_id": "wf-data16_ant_simple_minimal_ocr-eval",
        "label": "Workflow on data 16_ant_simple_minimal_ocr",
        "metadata": {
            "ocr_workflow": {
                "@id": "https://github.com/OCR-D/quiver-back-end/blob/main/workflows/ocrd_workflows/minimal_ocr.txt",
                "label": "OCR Workflow minimal_ocr"
            },
            "eval_workflow": {
                "@id": "https://github.com/OCR-D/quiver-back-end/blob/main/workflows/ocrd_workflows/dinglehopper_eval.txt",
                "label": "Evaluation Workflow dinglehopper_eval"
            },
            "gt_workspace": {
                "@id": "https://github.com/OCR-D/quiver-data/blob/main/16_ant_simple_minimal_ocr.ocrd.zip",
                "label": "GT workspace 16th century Antiqua simple layout"
            },
            "ocr_workspace": {
                "@id": "https://github.com/OCR-D/quiver-back-end/blob/main/workflows/results/16_ant_simple_minimal_ocr_ocr.zip",
                "label": "OCR workspace for 16_ant_simple_minimal_ocr"
            },
            "eval_workspace": {
                "@id": "https://github.com/OCR-D/quiver-back-end/blob/main/workflows/results/16_ant_simple_minimal_ocr_evaluation.zip",
                "label": "Evaluation workspace for 16_ant_simple_minimal_ocr"
            },
            "workflow_steps": {
                "ocrd-tesserocr-recognize": "{\"segmentation_level\": \"region\", \"textequiv_level\": \"word\", \"find_tables\": true, \"model\": \"Fraktur_GT4HistOCR\", \"dpi\": 0, \"padding\": 0, \"overwrite_segments\": false, \"overwrite_text\": true, \"shrink_polygons\": false, \"block_polygons\": false, \"find_staves\": false, \"sparse_text\": false, \"raw_lines\": false, \"char_whitelist\": \"\", \"char_blacklist\": \"\", \"char_unblacklist\": \"\", \"tesseract_parameters\": {}, \"xpath_parameters\": {}, \"xpath_model\": {}, \"auto_model\": false, \"oem\": \"DEFAULT\"}"
            },
            "workflow_model": "Fraktur_GT4HistOCR",
            "document_metadata": {
                "data_properties": {
                    "fonts": [
                        "Antiqua"
                    ],
                    "publication_century": "1500-1600",
                    "publication_decade": "",
                    "publication_year": "16th century",
                    "number_of_pages": 3,
                    "layout": "simple"
                }
            }
        },
        "evaluation_results": {
            "document_wide": {
                "wall_time": 11267,
                "cer": 0.07452119312897007,
                "cer_min_max": [
                    0.037037037037037035,
                    0.12354651162790697
                ]
            },
            "by_page": [
                {
                    "page_id": "phys_0007",
                    "cer": 0.0629800307219662
                },
                {
                    "page_id": "phys_0013",
                    "cer": 0.12354651162790697
                },
                {
                    "page_id": "phys_0014",
                    "cer": 0.037037037037037035
                }
            ]
        }
    }
]